CHANGES.rst
CONTRIBUTORS.rst
MANIFEST.in
README.rst
setup.py
src/propertyshelf/__init__.py
src/propertyshelf.fabfile.plone.egg-info/PKG-INFO
src/propertyshelf.fabfile.plone.egg-info/SOURCES.txt
src/propertyshelf.fabfile.plone.egg-info/dependency_links.txt
src/propertyshelf.fabfile.plone.egg-info/entry_points.txt
src/propertyshelf.fabfile.plone.egg-info/namespace_packages.txt
src/propertyshelf.fabfile.plone.egg-info/not-zip-safe
src/propertyshelf.fabfile.plone.egg-info/requires.txt
src/propertyshelf.fabfile.plone.egg-info/top_level.txt
src/propertyshelf/fabfile/__init__.py
src/propertyshelf/fabfile/plone/__init__.py
src/propertyshelf/fabfile/plone/bootstrap.py
src/propertyshelf/fabfile/plone/client.py
src/propertyshelf/fabfile/plone/database.py
src/propertyshelf/fabfile/plone/frontend.py
src/propertyshelf/fabfile/plone/roles.py
src/propertyshelf/fabfile/plone/utils.py