Metadata-Version: 1.1
Name: propertyshelf.fabfile.plone
Version: 0.1
Summary: Deploy and manage Propertyshelf Plone applications using Fabric.
Home-page: https://github.com/propertyshelf/propertyshelf.fabfile.plone
Author: Propertyshelf, Inc.
Author-email: development@propertyshelf.com
License: BSD
Download-URL: http://pypi.python.org/pypi/propertyshelf.fabfile.plone
Keywords: fabric python plone deployment
Platform: UNKNOWN
Classifier: Programming Language :: Python
